{"initial_mass": [0.782, 0.023], "initial_Zinit": [0.02, 0], "initial_Yinit": [0.28, 0], "initial_MLT": [2, 0], "star_age": [3, 0], "calc_effective_T": [4700, 65], "radius": [0.7108, 0.0142], "luminosity": [0.21, 0.02], "star_feh": [-0.17, 0.032], "nu_0_20": [4317.16, 1.22], "nu_0_21": [4517.63, 0.81], "nu_0_22": [4719.74, 0.88], "nu_0_23": [4919.4, 0.76], "nu_0_24": [5121.1, 0.55], "nu_0_25": [5321.16, 0.93], "nu_0_26": [5522.41, 1000000000.0], "nu_0_27": [5723.66, 1000000000.0], "nu_0_28": [5932.87, 1000000000.0], "nu_0_29": [6134.12, 0.99], "nu_0_30": [6338.29, 0.88], "dnu": [201.25, 0.16], "nu_max": [5265, 110]}